{"thoughts": [{"thumbThought": "/assets/content/thoughts/thoughts-image/1/thumbnail-image.jpg", "id": 1, "thought": "werfjewohnrwlekn weifnwle;fmwweeff", "name": "vito", "position": "Intern", "date": "2019-09-09"}, {"thumbThought": "/assets/content/thoughts/thoughts-image/2/thumbnail-image.jpg", "id": 2, "thought": "sfdlksfmdksjfnfklfklfms;dfklmlsdmlksdlfsdf,sd", "name": "Elvin", "position": "Employee", "date": "2019-09-09"}, {"position": "intern", "id": 3, "name": "test", "thumbThought": null, "date": "2019-09-16", "thought": "sdfklsfbfhsoflknekjnfslkdfmd"}]}